docbr/__init__.py
docbr/attributes.py
docbr/doctypes.py
docbr/api/__init__.py
docbr/api/facade.py
docbr/core/__init__.py
docbr/core/_io.py
docbr/core/_utils.py
docbr/core/checkdigit/__init__.py
docbr/core/checkdigit/_template.py
docbr/core/checkdigit/documents.py
docbr/core/regexp/__init__.py
docbr/core/regexp/_template.py
docbr/core/regexp/documents.py
docbr/core/tests/__init__.py
docbr/core/tests/test_io.py
docbr/core/tests/test_utils.py
docbr/tests/__init__.py
docbr/tests/test_docbr.py
docbr-0.1.3.dist-info/LICENSE
docbr-0.1.3.dist-info/METADATA
docbr-0.1.3.dist-info/WHEEL
docbr-0.1.3.dist-info/top_level.txt
docbr-0.1.3.dist-info/RECORD
