Metadata-Version: 2.1
Name: docbr
Version: 0.1.3
Summary: Validate Brazilian documents at scale.
Home-page: https://github.com/fontes-mrc/docbr
Author: Maurício Adriano Fontes
Author-email: suporte@mfontes.dev
License: MIT License
Classifier: Programming Language :: Python :: 3
Classifier: License :: OSI Approved :: MIT License
Classifier: Operating System :: OS Independent
Requires-Python: >=3.8
License-File: LICENSE
